.bumpversion.cfg
.gitignore
LICENSE
README.md
requirements.txt
setup.py
dfbridge/__init__.py
dfbridge/dfbridge.py
dfbridge.egg-info/PKG-INFO
dfbridge.egg-info/SOURCES.txt
dfbridge.egg-info/dependency_links.txt
dfbridge.egg-info/requires.txt
dfbridge.egg-info/top_level.txt