Metadata-Version: 2.1
Name: dfbridge
Version: 0.0.2
Summary: Schematized pipeline operations on dataframes
Home-page: https://github.com/ceesem/dfbridge
Author: Casey Schneider-Mizell
Author-email: caseysm@gmail.com
License: UNKNOWN
Platform: UNKNOWN
License-File: LICENSE
